setup.cfg
setup.py
twitchwatcher/__init__.py
twitchwatcher.egg-info/PKG-INFO
twitchwatcher.egg-info/SOURCES.txt
twitchwatcher.egg-info/dependency_links.txt
twitchwatcher.egg-info/entry_points.txt
twitchwatcher.egg-info/requires.txt
twitchwatcher.egg-info/top_level.txt