Metadata-Version: 1.1
Name: twitchwatcher
Version: 0.0.1
Summary: A tiny wrapper for livestreamer to watch twitch streams
Home-page: https://github.com/MOZGIII/twitchwatcher
Author: MOZGIII
Author-email: mike-n@narod.ru
License: MIT
Keywords: twitch livestreamer stream twitch.tv
Platform: UNKNOWN
Classifier: Development Status :: 4 - Beta
Classifier: Intended Audience :: End Users/Desktop
Classifier: Topic :: Games/Entertainment
Classifier: Topic :: Internet
Classifier: Topic :: Multimedia :: Video :: Display
Classifier: License :: OSI Approved :: MIT License
Classifier: Programming Language :: Python :: 2
Classifier: Programming Language :: Python :: 3
